django_payments_khipu/KhipuProvider.py
django_payments_khipu/__init__.py
django_payments_khipu-2024.9.23.dist-info/LICENSE
django_payments_khipu-2024.9.23.dist-info/METADATA
django_payments_khipu-2024.9.23.dist-info/WHEEL
django_payments_khipu-2024.9.23.dist-info/RECORD
