Metadata-Version: 2.1
Name: django-payments-khipu
Version: 2024.9.23
Summary: Soporte Khipu para Django Payments
Home-page: https://www.khipu.com/page/guia-de-implementacion/
License: MIT
Keywords: khipu,pagos,django,payment,django-payments,pago
Author: Mario Hernandez
Author-email: mariofix@proton.me
Requires-Python: >=3.9,<4.0
Classifier: Development Status :: 4 - Beta
Classifier: Framework :: Django
Classifier: Intended Audience :: Developers
Classifier: Intended Audience :: Information Technology
Classifier: License :: OSI Approved :: MIT License
Classifier: Operating System :: OS Independent
Classifier: Programming Language :: Python :: 3
Classifier: Programming Language :: Python :: 3.9
Classifier: Programming Language :: Python :: 3.10
Classifier: Programming Language :: Python :: 3.11
Classifier: Programming Language :: Python :: 3.12
Classifier: Topic :: Software Development :: Libraries :: Python Modules
Requires-Dist: django-payments (>=2.0.0,<=3.1)
Requires-Dist: pykhipu (<=0.1.9)
Project-URL: Documentation, https://mariofix.github.io/django-payments-khipu/
Project-URL: Repository, https://github.com/mariofix/django-payments-khipu
